conf_tree/__init__.py
conf_tree/abstract.py
conf_tree/differ.py
conf_tree/environment.py
conf_tree/factory.py
conf_tree/models.py
conf_tree/parser.py
conf_tree/postproc.py
conf_tree/postproc_arista.py
conf_tree/postproc_cisco.py
conf_tree/postproc_huawei.py
conf_tree/searcher.py
conf_tree/serializer.py
conf_tree/vendors.py
conf_tree-0.1.1.dist-info/LICENSE
conf_tree-0.1.1.dist-info/METADATA
conf_tree-0.1.1.dist-info/WHEEL
conf_tree-0.1.1.dist-info/RECORD
