Metadata-Version: 2.1
Name: conf-tree
Version: 0.1.1
Summary: Parsing, filtering and diff calculation for network device configurations
License: MIT
Keywords: cisco,arista,huawei,network,automation,configuration
Author: Alexander Ignatov
Author-email: ignatov.alx@gmail.com
Requires-Python: >=3.10
Classifier: License :: OSI Approved :: MIT License
Classifier: Programming Language :: Python :: 3
Classifier: Programming Language :: Python :: 3.10
Classifier: Programming Language :: Python :: 3.11
Classifier: Programming Language :: Python :: 3.12
Classifier: Programming Language :: Python :: 3.13
Requires-Dist: pyyaml (>=6.0.2,<7.0.0)
